blackadder/__init__.py
blackadder/main.py
blackadder/vyper_compat.py
blackadder-0.1.1.dist-info/LICENSE.md
blackadder-0.1.1.dist-info/METADATA
blackadder-0.1.1.dist-info/WHEEL
blackadder-0.1.1.dist-info/entry_points.txt
blackadder-0.1.1.dist-info/top_level.txt
blackadder-0.1.1.dist-info/RECORD
